redisobjects/__init__.py
redisobjects/connect.py
redisobjects/decorators.py
redisobjects/redis_adapter.py
redisobjects/redis_atom.py
redisobjects/redis_dict.py
redisobjects/redis_entity_space.py
redisobjects/redis_index_atom.py
redisobjects/redis_index_set.py
redisobjects/redis_integer.py
redisobjects/redis_keyspace.py
redisobjects/redis_list.py
redisobjects/redis_manager.py
redisobjects/redis_object.py
redisobjects/redis_object_factory.py
redisobjects/redis_set.py
redisobjects/redis_transaction.py
redisobjects/serializers/__init__.py
redisobjects/serializers/datetime_serializer.py
redisobjects/serializers/generic_serializer.py
redisobjects/serializers/identity_serializer.py
redisobjects/serializers/json_serializer.py
redisobjects/serializers/string_serializer.py
redisobjects/serializers/tuple_serializer.py
redisobjects/serializers/uuid_serializer.py
redisobjects-0.7.8.dist-info/LICENSE
redisobjects-0.7.8.dist-info/METADATA
redisobjects-0.7.8.dist-info/WHEEL
redisobjects-0.7.8.dist-info/top_level.txt
redisobjects-0.7.8.dist-info/RECORD
