Metadata-Version: 2.1
Name: redisobjects
Version: 0.7.8
Summary: Object-oriented wrapper for aioredis.
Home-page: https://gitlab.com/jchmb/redisobjects
Author: Jochem Barelds
Author-email: barelds.jochem@gmail.com
License: MIT
Platform: UNKNOWN
Classifier: Topic :: Database
Classifier: Topic :: Database :: Database Engines/Servers
Classifier: License :: OSI Approved :: MIT License
Classifier: Programming Language :: Python :: 3.6
Classifier: Programming Language :: Python :: 3.7
Classifier: Intended Audience :: Developers
Classifier: Development Status :: 3 - Alpha
Requires-Python: >=3.6
Requires-Dist: aioredis
Requires-Dist: shortuuid
Requires-Dist: fakeredis
